acme_dw/__init__.py
acme_dw/_main.py
acme_dw/dw.py
acme_dw-0.0.5.dist-info/METADATA
acme_dw-0.0.5.dist-info/WHEEL
acme_dw-0.0.5.dist-info/entry_points.txt
acme_dw-0.0.5.dist-info/top_level.txt
acme_dw-0.0.5.dist-info/RECORD
