Metadata-Version: 2.4
Name: acme_dw
Version: 0.0.5
Summary: Simple data warehouse using S3
Author-email: guner.stan@gmail.com
Project-URL: homepage, https://example.com
Project-URL: repository, https://example.com
Classifier: Programming Language :: Python :: 3.12
Requires-Python: >=3.9
Requires-Dist: python-dotenv
Requires-Dist: pandas
Requires-Dist: acme_s3>=0.0.5
Requires-Dist: pyarrow
Requires-Dist: polars
Provides-Extra: dev
Requires-Dist: pytest; extra == "dev"
Requires-Dist: uv; extra == "dev"
Requires-Dist: mkdocs; extra == "dev"
Requires-Dist: mkdocs-material; extra == "dev"
Requires-Dist: mkdocstrings[python]; extra == "dev"
Requires-Dist: jupyterlab; extra == "dev"
